{"index":{"links":{"/":[{"source":"/","target":"/notes/user","text":"nous les utilisateurs"},{"source":"/","target":"/notes/numcrea","text":"Numérique créatif des Grands Voisins"},{"source":"/","target":"/notes/services","text":"services internet pour remplacer les GAFAM"},{"source":"/","target":"/notes/infrastructure","text":"notre infrastructure"}],"/notes/numcrea":[{"source":"/notes/numcrea","target":"/notes/services","text":"services de remplacement des Gafam"}],"/notes/services":[{"source":"/notes/services","target":"/notes/interdependance","text":"d'interdépendance numérique"},{"source":"/notes/services","target":"/notes/resdigitacom-mail","text":"mail.resdigita.com"},{"source":"/notes/services","target":"/notes/numcrea","text":"Numérique créatif des Grands Voisins"}],"/notes/user":[{"source":"/notes/user","target":"/notes/services","text":"nos services"}]},"backlinks":{"/notes/infrastructure":[{"source":"/","target":"/notes/infrastructure","text":"notre infrastructure"}],"/notes/interdependance":[{"source":"/notes/services","target":"/notes/interdependance","text":"d'interdépendance numérique"}],"/notes/numcrea":[{"source":"/","target":"/notes/numcrea","text":"Numérique créatif des Grands Voisins"},{"source":"/notes/services","target":"/notes/numcrea","text":"Numérique créatif des Grands Voisins"}],"/notes/resdigitacom-mail":[{"source":"/notes/services","target":"/notes/resdigitacom-mail","text":"mail.resdigita.com"}],"/notes/services":[{"source":"/","target":"/notes/services","text":"services internet pour remplacer les GAFAM"},{"source":"/notes/numcrea","target":"/notes/services","text":"services de remplacement des Gafam"},{"source":"/notes/user","target":"/notes/services","text":"nos services"}],"/notes/user":[{"source":"/","target":"/notes/user","text":"nous les utilisateurs"}]}},"links":[{"source":"/","target":"/notes/user","text":"nous les utilisateurs"},{"source":"/","target":"/notes/numcrea","text":"Numérique créatif des Grands Voisins"},{"source":"/","target":"/notes/services","text":"services internet pour remplacer les GAFAM"},{"source":"/","target":"/notes/infrastructure","text":"notre infrastructure"},{"source":"/notes/numcrea","target":"/notes/services","text":"services de remplacement des Gafam"},{"source":"/notes/services","target":"/notes/interdependance","text":"d'interdépendance numérique"},{"source":"/notes/services","target":"/notes/resdigitacom-mail","text":"mail.resdigita.com"},{"source":"/notes/services","target":"/notes/numcrea","text":"Numérique créatif des Grands Voisins"},{"source":"/notes/user","target":"/notes/services","text":"nos services"}]}